typedb/__init__.py
typedb/client.py
typedb/api/__init__.py
typedb/api/answer/__init__.py
typedb/api/answer/concept_map.py
typedb/api/answer/concept_map_group.py
typedb/api/answer/numeric.py
typedb/api/answer/numeric_group.py
typedb/api/concept/__init__.py
typedb/api/concept/concept.py
typedb/api/concept/concept_manager.py
typedb/api/concept/thing/__init__.py
typedb/api/concept/thing/attribute.py
typedb/api/concept/thing/entity.py
typedb/api/concept/thing/relation.py
typedb/api/concept/thing/thing.py
typedb/api/concept/type/__init__.py
typedb/api/concept/type/attribute_type.py
typedb/api/concept/type/entity_type.py
typedb/api/concept/type/relation_type.py
typedb/api/concept/type/role_type.py
typedb/api/concept/type/thing_type.py
typedb/api/concept/type/type.py
typedb/api/concept/value/__init__.py
typedb/api/concept/value/value.py
typedb/api/connection/__init__.py
typedb/api/connection/client.py
typedb/api/connection/credential.py
typedb/api/connection/database.py
typedb/api/connection/options.py
typedb/api/connection/session.py
typedb/api/connection/transaction.py
typedb/api/connection/user.py
typedb/api/logic/__init__.py
typedb/api/logic/explanation.py
typedb/api/logic/logic_manager.py
typedb/api/logic/rule.py
typedb/api/query/__init__.py
typedb/api/query/future.py
typedb/api/query/query_manager.py
typedb/common/__init__.py
typedb/common/exception.py
typedb/common/label.py
typedb/common/concurrent/__init__.py
typedb/common/concurrent/atomic.py
typedb/common/concurrent/lock.py
typedb/common/concurrent/scheduled_executor.py
typedb/common/rpc/__init__.py
typedb/common/rpc/request_builder.py
typedb/common/rpc/stub.py
typedb/concept/__init__.py
typedb/concept/concept.py
typedb/concept/concept_manager.py
typedb/concept/answer/__init__.py
typedb/concept/answer/concept_map.py
typedb/concept/answer/concept_map_group.py
typedb/concept/answer/numeric.py
typedb/concept/answer/numeric_group.py
typedb/concept/proto/__init__.py
typedb/concept/proto/concept_proto_builder.py
typedb_client-2.18.2.dist-info/METADATA
typedb_client-2.18.2.dist-info/WHEEL
typedb_client-2.18.2.dist-info/top_level.txt
typedb_client-2.18.2.dist-info/RECORD
