Metadata-Version: 2.1
Name: typedb-client
Version: 2.18.2
Summary: TypeDB Client for Python
Home-page: https://github.com/vaticle/typedb-client-python/
Author: Vaticle
Author-email: community@vaticle.com
License: Apache-2.0
Keywords: typedb database graph knowledgebase knowledge-engineering
Classifier: Programming Language :: Python
Classifier: Programming Language :: Python :: 3
Classifier: Programming Language :: Python :: 3.5
Classifier: Programming Language :: Python :: 3.6
Classifier: Programming Language :: Python :: 3.7
Classifier: Programming Language :: Python :: 3.8
Classifier: Programming Language :: Python :: 3.9
Classifier: License :: OSI Approved :: Apache Software License
Classifier: Operating System :: OS Independent
Classifier: Intended Audience :: Developers
Classifier: Intended Audience :: Science/Research
Classifier: Environment :: Console
Classifier: Topic :: Database :: Front-Ends
Requires-Python: >0
